LICENSE.md
MANIFEST.in
README.md
setup.cfg
setup.py
netflix_roulette/__init__.py
netflix_roulette/constants.py
netflix_roulette/exceptions.py
netflix_roulette/netflix_roulette_api.py
netflix_roulette/request.py
netflix_roulette/util.py
netflix_roulette.egg-info/PKG-INFO
netflix_roulette.egg-info/SOURCES.txt
netflix_roulette.egg-info/dependency_links.txt
netflix_roulette.egg-info/requires.txt
netflix_roulette.egg-info/top_level.txt
netflix_roulette.egg-info/zip-safe