Metadata-Version: 1.1
Name: netflix-roulette
Version: 0.23
Summary: A simple python wrapper for the Netflix Roulette API
Home-page: https://github.com/tizz98/netflix_roulette
Author: Elijah Wilson
Author-email: elijah@elijahwilson.me
License: GNU General Public License v3.0
Download-URL: https://github.com/tizz98/netflix_roulette/tarball/0.23
Keywords: netflix roulette netflixroulette netflix_roulette api
Platform: UNKNOWN
Classifier: Development Status :: 4 - Beta
Classifier: Intended Audience :: Developers
Classifier: Topic :: Software Development :: Libraries
Classifier: License :: OSI Approved :: GNU General Public License v3 (GPLv3)
Classifier: Programming Language :: Python :: 2
Classifier: Programming Language :: Python :: 2.6
Classifier: Programming Language :: Python :: 2.7
Classifier: Programming Language :: Python :: 3
Classifier: Programming Language :: Python :: 3.3
Classifier: Programming Language :: Python :: 3.4
